{
  "meta": {
    "slug": "colossal-cave",
    "title": "Colossal Cave Adventure",
    "description": "The classic text adventure by Will Crowther and Don Woods. Explore a vast cave system, collect treasures, and avoid dangers.",
    "seed": 42,
    "theme": "cave",
    "aiThinkingMessages": [
      "A hollow wind echoes through the cavern...",
      "Water drips somewhere in the darkness...",
      "The cave seems to shift around you...",
      "Shadows dance at the edge of your lamp light...",
      "You hear a faint rumble from deep below..."
    ]
  },
  "properties": [
    {
      "name": "plantSize",
      "description": "Size of the beanstalk plant",
      "schema": {
        "type": "string",
        "enum": [
          "tiny",
          "tall",
          "huge"
        ]
      }
    },
    {
      "name": "friendly",
      "description": "Whether an NPC is friendly to the player",
      "schema": {
        "type": "boolean"
      },
      "defaultValue": false
    },
    {
      "name": "following",
      "description": "Whether an NPC is following the player",
      "schema": {
        "type": "boolean"
      },
      "defaultValue": false
    },
    {
      "name": "questioning",
      "description": "Whether the dragon is asking about bare hands",
      "schema": {
        "type": "boolean"
      },
      "defaultValue": false
    },
    {
      "name": "alive",
      "description": "Whether an NPC is alive",
      "schema": {
        "type": "boolean"
      },
      "defaultValue": true
    },
    {
      "name": "treasured",
      "description": "Whether the troll has been paid with a treasure",
      "schema": {
        "type": "boolean"
      },
      "defaultValue": false
    },
    {
      "name": "spotted",
      "description": "Whether the pirate has been spotted",
      "schema": {
        "type": "boolean"
      },
      "defaultValue": false
    },
    {
      "name": "rich",
      "description": "Whether the pirate has stolen treasure",
      "schema": {
        "type": "boolean"
      },
      "defaultValue": false
    },
    {
      "name": "retired",
      "description": "Whether the pirate has retired",
      "schema": {
        "type": "boolean"
      },
      "defaultValue": false
    },
    {
      "name": "scored_take",
      "description": "Whether take-score has been awarded for this treasure",
      "schema": {
        "type": "boolean"
      },
      "defaultValue": false
    },
    {
      "name": "scored_found",
      "description": "Whether find-score has been awarded for this treasure",
      "schema": {
        "type": "boolean"
      },
      "defaultValue": false
    },
    {
      "name": "caveClosing",
      "description": "Whether the cave closing sequence is active",
      "schema": {
        "type": "boolean"
      },
      "defaultValue": false
    },
    {
      "name": "caveClosed",
      "description": "Whether the cave has fully closed",
      "schema": {
        "type": "boolean"
      },
      "defaultValue": false
    },
    {
      "name": "closingCountdown",
      "description": "Turns remaining until cave closes",
      "schema": {
        "type": "number"
      },
      "defaultValue": 0
    },
    {
      "name": "gameOver",
      "description": "Whether the game has ended",
      "schema": {
        "type": "boolean"
      },
      "defaultValue": false
    },
    {
      "name": "feeCount",
      "description": "Progress through the fee-fie-foe-foo magic word sequence",
      "schema": {
        "type": "number"
      },
      "defaultValue": 0
    },
    {
      "name": "dflag",
      "description": "Dwarf activation level (0=none, 1=intro, 2=active)",
      "schema": {
        "type": "integer"
      }
    },
    {
      "name": "prevRoom",
      "description": "Previous room for dwarf movement (avoid backtracking)",
      "schema": {
        "type": "string"
      }
    },
    {
      "name": "dead",
      "description": "Whether this dwarf has been killed",
      "schema": {
        "type": "boolean"
      }
    }
  ]
}
